pyfmu/__init__.py
pyfmu/pyfmu_cli.py
pyfmu/types.py
pyfmu/utils.py
pyfmu/builder/__init__.py
pyfmu/builder/export.py
pyfmu/builder/generate.py
pyfmu/builder/utils.py
pyfmu/builder/validate.py
pyfmu/fmi2/__init__.py
pyfmu/fmi2/exception.py
pyfmu/fmi2/logging.py
pyfmu/fmi2/slave.py
pyfmu/fmi2/slaveContext.py
pyfmu/fmi2/types.py
pyfmu/fmi2/validation.py
pyfmu/resources/__init__.py
pyfmu/resources/resources.py
pyfmu/resources/templates/fmu.py.j2
pyfmu/resources/validation/coe.jar
pyfmu/resources/validation/coe.log
pyfmu/resources/validation/fmuCheck.linux64
pyfmu/resources/validation/fmuCheck.win64.exe
pyfmu/resources/wrapper/binaries/linux64/pyfmu.so
pyfmu/resources/wrapper/binaries/win64/pyfmu.dll
pyfmu-0.0.4.dist-info/METADATA
pyfmu-0.0.4.dist-info/WHEEL
pyfmu-0.0.4.dist-info/entry_points.txt
pyfmu-0.0.4.dist-info/top_level.txt
pyfmu-0.0.4.dist-info/RECORD
